[
  {
    "id": 1,
    "day": "monday",
    "date": "2025-10-01",
    "time": 8,
    "status": "available",
    "owner": null
  },
  {
    "id": 2,
    "day": "monday",
    "date": "2025-10-01",
    "time": 9,
    "status": "available",
    "owner": null
  },
  {
    "id": 3,
    "day": "monday",
    "date": "2025-10-01",
    "time": 10,
    "status": "booked",
    "owner": "User3"
  },
  {
    "id": 4,
    "day": "monday",
    "date": "2025-10-01",
    "time": 11,
    "status": "available",
    "owner": null
  },
  {
    "id": 5,
    "day": "monday",
    "date": "2025-10-01",
    "time": 12,
    "status": "available",
    "owner": null
  },
  {
    "id": 6,
    "day": "monday",
    "date": "2025-10-01",
    "time": 13,
    "status": "booked",
    "owner": "User6"
  },
  {
    "id": 7,
    "day": "monday",
    "date": "2025-10-01",
    "time": 14,
    "status": "available",
    "owner": null
  },
  {
    "id": 8,
    "day": "monday",
    "date": "2025-10-01",
    "time": 15,
    "status": "available",
    "owner": null
  },
  {
    "id": 9,
    "day": "monday",
    "date": "2025-10-01",
    "time": 16,
    "status": "booked",
    "owner": "User9"
  },
  {
    "id": 10,
    "day": "monday",
    "date": "2025-10-01",
    "time": 17,
    "status": "available",
    "owner": null
  },

  {
    "id": 11,
    "day": "tuesday",
    "date": "2025-10-02",
    "time": 8,
    "status": "available",
    "owner": null
  },
  {
    "id": 12,
    "day": "tuesday",
    "date": "2025-10-02",
    "time": 9,
    "status": "booked",
    "owner": "User12"
  },
  {
    "id": 13,
    "day": "tuesday",
    "date": "2025-10-02",
    "time": 10,
    "status": "available",
    "owner": null
  },
  {
    "id": 14,
    "day": "tuesday",
    "date": "2025-10-02",
    "time": 11,
    "status": "available",
    "owner": null
  },
  {
    "id": 15,
    "day": "tuesday",
    "date": "2025-10-02",
    "time": 12,
    "status": "booked",
    "owner": "User15"
  },
  {
    "id": 16,
    "day": "tuesday",
    "date": "2025-10-02",
    "time": 13,
    "status": "available",
    "owner": null
  },
  {
    "id": 17,
    "day": "tuesday",
    "date": "2025-10-02",
    "time": 14,
    "status": "available",
    "owner": null
  },
  {
    "id": 18,
    "day": "tuesday",
    "date": "2025-10-02",
    "time": 15,
    "status": "booked",
    "owner": "User18"
  },
  {
    "id": 19,
    "day": "tuesday",
    "date": "2025-10-02",
    "time": 16,
    "status": "available",
    "owner": null
  },
  {
    "id": 20,
    "day": "tuesday",
    "date": "2025-10-02",
    "time": 17,
    "status": "available",
    "owner": null
  },

  {
    "id": 21,
    "day": "wednesday",
    "date": "2025-10-03",
    "time": 8,
    "status": "booked",
    "owner": "User21"
  },
  {
    "id": 22,
    "day": "wednesday",
    "date": "2025-10-03",
    "time": 9,
    "status": "available",
    "owner": null
  },
  {
    "id": 23,
    "day": "wednesday",
    "date": "2025-10-03",
    "time": 10,
    "status": "available",
    "owner": null
  },
  {
    "id": 24,
    "day": "wednesday",
    "date": "2025-10-03",
    "time": 11,
    "status": "booked",
    "owner": "User24"
  },
  {
    "id": 25,
    "day": "wednesday",
    "date": "2025-10-03",
    "time": 12,
    "status": "available",
    "owner": null
  },
  {
    "id": 26,
    "day": "wednesday",
    "date": "2025-10-03",
    "time": 13,
    "status": "available",
    "owner": null
  },
  {
    "id": 27,
    "day": "wednesday",
    "date": "2025-10-03",
    "time": 14,
    "status": "booked",
    "owner": "User27"
  },
  {
    "id": 28,
    "day": "wednesday",
    "date": "2025-10-03",
    "time": 15,
    "status": "available",
    "owner": null
  },
  {
    "id": 29,
    "day": "wednesday",
    "date": "2025-10-03",
    "time": 16,
    "status": "available",
    "owner": null
  },
  {
    "id": 30,
    "day": "wednesday",
    "date": "2025-10-03",
    "time": 17,
    "status": "booked",
    "owner": "User30"
  },

  {
    "id": 31,
    "day": "thursday",
    "date": "2025-10-04",
    "time": 8,
    "status": "available",
    "owner": null
  },
  {
    "id": 32,
    "day": "thursday",
    "date": "2025-10-04",
    "time": 9,
    "status": "available",
    "owner": null
  },
  {
    "id": 33,
    "day": "thursday",
    "date": "2025-10-04",
    "time": 10,
    "status": "booked",
    "owner": "User33"
  },
  {
    "id": 34,
    "day": "thursday",
    "date": "2025-10-04",
    "time": 11,
    "status": "available",
    "owner": null
  },
  {
    "id": 35,
    "day": "thursday",
    "date": "2025-10-04",
    "time": 12,
    "status": "available",
    "owner": null
  },
  {
    "id": 36,
    "day": "thursday",
    "date": "2025-10-04",
    "time": 13,
    "status": "booked",
    "owner": "User36"
  },
  {
    "id": 37,
    "day": "thursday",
    "date": "2025-10-04",
    "time": 14,
    "status": "available",
    "owner": null
  },
  {
    "id": 38,
    "day": "thursday",
    "date": "2025-10-04",
    "time": 15,
    "status": "available",
    "owner": null
  },
  {
    "id": 39,
    "day": "thursday",
    "date": "2025-10-04",
    "time": 16,
    "status": "booked",
    "owner": "User39"
  },
  {
    "id": 40,
    "day": "thursday",
    "date": "2025-10-04",
    "time": 17,
    "status": "available",
    "owner": null
  },

  {
    "id": 41,
    "day": "friday",
    "date": "2025-10-05",
    "time": 8,
    "status": "available",
    "owner": null
  },
  {
    "id": 42,
    "day": "friday",
    "date": "2025-10-05",
    "time": 9,
    "status": "booked",
    "owner": "User42"
  },
  {
    "id": 43,
    "day": "friday",
    "date": "2025-10-05",
    "time": 10,
    "status": "available",
    "owner": null
  },
  {
    "id": 44,
    "day": "friday",
    "date": "2025-10-05",
    "time": 11,
    "status": "available",
    "owner": null
  },
  {
    "id": 45,
    "day": "friday",
    "date": "2025-10-05",
    "time": 12,
    "status": "booked",
    "owner": "User45"
  },
  {
    "id": 46,
    "day": "friday",
    "date": "2025-10-05",
    "time": 13,
    "status": "available",
    "owner": null
  },
  {
    "id": 47,
    "day": "friday",
    "date": "2025-10-05",
    "time": 14,
    "status": "available",
    "owner": null
  },
  {
    "id": 48,
    "day": "friday",
    "date": "2025-10-05",
    "time": 15,
    "status": "booked",
    "owner": "User48"
  },
  {
    "id": 49,
    "day": "friday",
    "date": "2025-10-05",
    "time": 16,
    "status": "available",
    "owner": null
  },
  {
    "id": 50,
    "day": "friday",
    "date": "2025-10-05",
    "time": 17,
    "status": "available",
    "owner": null
  },

  {
    "id": 51,
    "day": "saturday",
    "date": "2025-10-06",
    "time": 8,
    "status": "booked",
    "owner": "User51"
  },
  {
    "id": 52,
    "day": "saturday",
    "date": "2025-10-06",
    "time": 9,
    "status": "available",
    "owner": null
  },
  {
    "id": 53,
    "day": "saturday",
    "date": "2025-10-06",
    "time": 10,
    "status": "available",
    "owner": null
  },
  {
    "id": 54,
    "day": "saturday",
    "date": "2025-10-06",
    "time": 11,
    "status": "booked",
    "owner": "User54"
  },
  {
    "id": 55,
    "day": "saturday",
    "date": "2025-10-06",
    "time": 12,
    "status": "available",
    "owner": null
  },
  {
    "id": 56,
    "day": "saturday",
    "date": "2025-10-06",
    "time": 13,
    "status": "available",
    "owner": null
  },
  {
    "id": 57,
    "day": "saturday",
    "date": "2025-10-06",
    "time": 14,
    "status": "booked",
    "owner": "User57"
  },
  {
    "id": 58,
    "day": "saturday",
    "date": "2025-10-06",
    "time": 15,
    "status": "available",
    "owner": null
  },
  {
    "id": 59,
    "day": "saturday",
    "date": "2025-10-06",
    "time": 16,
    "status": "available",
    "owner": null
  },
  {
    "id": 60,
    "day": "saturday",
    "date": "2025-10-06",
    "time": 17,
    "status": "booked",
    "owner": "User60"
  },

  {
    "id": 61,
    "day": "sunday",
    "date": "2025-10-07",
    "time": 8,
    "status": "available",
    "owner": null
  },
  {
    "id": 62,
    "day": "sunday",
    "date": "2025-10-07",
    "time": 9,
    "status": "available",
    "owner": null
  },
  {
    "id": 63,
    "day": "sunday",
    "date": "2025-10-07",
    "time": 10,
    "status": "booked",
    "owner": "User63"
  },
  {
    "id": 64,
    "day": "sunday",
    "date": "2025-10-07",
    "time": 11,
    "status": "available",
    "owner": null
  },
  {
    "id": 65,
    "day": "sunday",
    "date": "2025-10-07",
    "time": 12,
    "status": "available",
    "owner": null
  },
  {
    "id": 66,
    "day": "sunday",
    "date": "2025-10-07",
    "time": 13,
    "status": "booked",
    "owner": "User66"
  },
  {
    "id": 67,
    "day": "sunday",
    "date": "2025-10-07",
    "time": 14,
    "status": "available",
    "owner": null
  },
  {
    "id": 68,
    "day": "sunday",
    "date": "2025-10-07",
    "time": 15,
    "status": "available",
    "owner": null
  },
  {
    "id": 69,
    "day": "sunday",
    "date": "2025-10-07",
    "time": 16,
    "status": "booked",
    "owner": "User69"
  },
  {
    "id": 70,
    "day": "sunday",
    "date": "2025-10-07",
    "time": 17,
    "status": "available",
    "owner": null
  }
]
